pydantic_numpy/__init__.py
pydantic_numpy/helper/__init__.py
pydantic_numpy/helper/annotation.py
pydantic_numpy/helper/typing.py
pydantic_numpy/helper/validation.py
pydantic_numpy/model.py
pydantic_numpy/typing/__init__.py
pydantic_numpy/typing/type_safe/__init__.py
pydantic_numpy/typing/type_safe/i_dimensional.py
pydantic_numpy/typing/type_safe/ii_dimensional.py
pydantic_numpy/typing/type_safe/iii_dimensional.py
pydantic_numpy/typing/type_safe/n_dimensional.py
pydantic_numpy/typing/with_loader/__init__.py
pydantic_numpy/typing/with_loader/i_dimensional.py
pydantic_numpy/typing/with_loader/ii_dimensional.py
pydantic_numpy/typing/with_loader/iii_dimensional.py
pydantic_numpy/typing/with_loader/n_dimensional.py
pydantic_numpy/util.py
pydantic_numpy-9.0.1.dist-info/WHEEL
pydantic_numpy-9.0.1.dist-info/METADATA
pydantic_numpy-9.0.1.dist-info/RECORD
