Metadata-Version: 2.3
Name: pydantic-numpy
Version: 9.0.1
Summary: Pydantic Model integration of the NumPy array
Keywords: pydantic,numpy,typing,validation
Author: Can H. Tartanoglu, Christoph Heindl
Author-email: Can H. Tartanoglu <gpg@rotas.mozmail.com>
License: BSD-3-Clause
Classifier: Development Status :: 5 - Production/Stable
Classifier: Topic :: Software Development :: Libraries :: Python Modules
Classifier: Operating System :: OS Independent
Requires-Dist: compress-pickle[lz4]
Requires-Dist: ruamel-yaml==0.18
Requires-Dist: numpy~=2.3.5
Requires-Dist: pydantic~=2.12.5
Requires-Dist: semver~=3.0.4
Requires-Python: >=3.11, <3.15
Project-URL: Homepage, https://github.com/caniko/pydantic-numpy
